CHANGELOG.md
MANIFEST.in
README.md
README.zh-CN.md
requirements.in
setup.cfg
setup.py
api_basebone/__init__.py
api_basebone/admin.py
api_basebone/apps.py
api_basebone/models.py
api_basebone/settings.py
api_basebone/tasks.py
api_basebone/urls.py
api_basebone/app/__init__.py
api_basebone/app/client_urls.py
api_basebone/app/manage_urls.py
api_basebone/app/account/__init__.py
api_basebone/app/account/forms.py
api_basebone/app/account/views.py
api_basebone/app/upload/__init__.py
api_basebone/app/upload/views.py
api_basebone/bsm/__init__.py
api_basebone/bsm/admin.py
api_basebone/bsm/api.py
api_basebone/bsm/functions/__init__.py
api_basebone/const/__init__.py
api_basebone/const/field_map.py
api_basebone/core/__init__.py
api_basebone/core/admin.py
api_basebone/core/const.py
api_basebone/core/decorators.py
api_basebone/core/drf_field.py
api_basebone/core/exceptions.py
api_basebone/core/fields.py
api_basebone/core/gmeta.py
api_basebone/core/object_model.py
api_basebone/core/widgets.py
api_basebone/db/__init__.py
api_basebone/db/query.py
api_basebone/drf/__init__.py
api_basebone/drf/authentication.py
api_basebone/drf/fields.py
api_basebone/drf/handler.py
api_basebone/drf/pagination.py
api_basebone/drf/permissions.py
api_basebone/drf/response.py
api_basebone/drf/routers.py
api_basebone/export/__init__.py
api_basebone/export/admin.py
api_basebone/export/fields.py
api_basebone/export/setting.py
api_basebone/export/specs.py
api_basebone/management/__init__.py
api_basebone/management/commands/__init__.py
api_basebone/management/commands/bsm_api_doc.py
api_basebone/management/commands/bsm_config.py
api_basebone/migrations/0001_initial.py
api_basebone/migrations/0002_auto_20190524_1155.py
api_basebone/migrations/0003_api_field_filter_parameter.py
api_basebone/migrations/0004_auto_20190910_2242.py
api_basebone/migrations/0005_auto_20190910_2244.py
api_basebone/migrations/0006_auto_20190910_2246.py
api_basebone/migrations/0007_auto_20190910_2247.py
django_lightning.egg-info/PKG-INFO
django_lightning.egg-info/SOURCES.txt
django_lightning.egg-info/dependency_links.txt
django_lightning.egg-info/not-zip-safe
django_lightning.egg-info/requires.txt
django_lightning.egg-info/top_level.txt
